code_graph_rag_mcp/__init__.py
code_graph_rag_mcp/build_extensions.py
code_graph_rag_mcp/server.py
code_graph_rag_mcp/chunker/__init__.py
code_graph_rag_mcp/chunker/builder.py
code_graph_rag_mcp/cli/__init__.py
code_graph_rag_mcp/cli/init_db.py
code_graph_rag_mcp/cli/main.py
code_graph_rag_mcp/cli/serve.py
code_graph_rag_mcp/config/__init__.py
code_graph_rag_mcp/config/loader.py
code_graph_rag_mcp/config/models.py
code_graph_rag_mcp/db/__init__.py
code_graph_rag_mcp/db/bootstrap.py
code_graph_rag_mcp/db/extensions.py
code_graph_rag_mcp/db/manager.py
code_graph_rag_mcp/db/operations.py
code_graph_rag_mcp/db/queries.py
code_graph_rag_mcp/db/schema.py
code_graph_rag_mcp/embedding/__init__.py
code_graph_rag_mcp/embedding/gemma.py
code_graph_rag_mcp/handlers/__init__.py
code_graph_rag_mcp/handlers/ingest.py
code_graph_rag_mcp/handlers/search.py
code_graph_rag_mcp/handlers/status.py
code_graph_rag_mcp/indexer/__init__.py
code_graph_rag_mcp/indexer/ingest.py
code_graph_rag_mcp/models/__init__.py
code_graph_rag_mcp/models/graph.py
code_graph_rag_mcp/native/__init__.py
code_graph_rag_mcp/native/bfsvtab.so
code_graph_rag_mcp/native/sqlite-vec0.so
code_graph_rag_mcp/parsers/__init__.py
code_graph_rag_mcp/parsers/base.py
code_graph_rag_mcp/parsers/detect.py
code_graph_rag_mcp/parsers/python.py
code_graph_rag_mcp/parsers/typescript.py
code_graph_rag_mcp/service/__init__.py
code_graph_rag_mcp/service/context.py
code_graph_rag_mcp/service/diagnostics.py
code_graph_rag_mcp/tools/__init__.py
code_graph_rag_mcp/tools/definitions.py
code_graph_rag_mcp/watcher/__init__.py
code_graph_rag_mcp/watcher/jobs.py
code_graph_rag_mcp/watcher/queue.py
code_graph_rag_mcp/watcher/service.py
code_graph_rag_mcp/watcher/worker.py
code_graph_rag_mcp-0.1.2.dist-info/METADATA
code_graph_rag_mcp-0.1.2.dist-info/WHEEL
code_graph_rag_mcp-0.1.2.dist-info/entry_points.txt
code_graph_rag_mcp-0.1.2.dist-info/top_level.txt
code_graph_rag_mcp-0.1.2.dist-info/RECORD
