Metadata-Version: 2.4
Name: code-graph-rag-mcp
Version: 0.1.2
Summary: Local-first code knowledge graph MCP server
Author: Andrew
License-Expression: MIT
Requires-Python: >=3.10
Requires-Dist: mcp>=0.1.0
Requires-Dist: pydantic>=2.6
Requires-Dist: watchfiles>=0.21
Requires-Dist: tree-sitter==0.21.1
Requires-Dist: tree-sitter-languages==1.9.1
Requires-Dist: PyYAML>=6.0
Requires-Dist: sqlite-utils>=3.36
Requires-Dist: typer>=0.9
Requires-Dist: numpy>=1.26
Provides-Extra: dev
Requires-Dist: pytest; extra == "dev"
Requires-Dist: pytest-asyncio; extra == "dev"
Requires-Dist: ruff; extra == "dev"
